avwx/__about__.py
avwx/__init__.py
avwx/base.py
avwx/exceptions.py
avwx/flight_path.py
avwx/load_utils.py
avwx/structs.py
avwx/current/__init__.py
avwx/current/airep.py
avwx/current/airsigmet.py
avwx/current/base.py
avwx/current/metar.py
avwx/current/notam.py
avwx/current/pirep.py
avwx/current/taf.py
avwx/data/__init__.py
avwx/data/build_aircraft.py
avwx/data/build_navaids.py
avwx/data/build_stations.py
avwx/data/mappers.py
avwx/data/files/aircraft.json
avwx/data/files/good_stations.txt
avwx/data/files/navaids.json
avwx/data/files/stations.json
avwx/forecast/__init__.py
avwx/forecast/base.py
avwx/forecast/gfs.py
avwx/forecast/nbm.py
avwx/parsing/__init__.py
avwx/parsing/core.py
avwx/parsing/remarks.py
avwx/parsing/speech.py
avwx/parsing/summary.py
avwx/parsing/sanitization/__init__.py
avwx/parsing/sanitization/base.py
avwx/parsing/sanitization/metar.py
avwx/parsing/sanitization/pirep.py
avwx/parsing/sanitization/taf.py
avwx/parsing/sanitization/cleaners/__init__.py
avwx/parsing/sanitization/cleaners/base.py
avwx/parsing/sanitization/cleaners/cleaners.py
avwx/parsing/sanitization/cleaners/cloud.py
avwx/parsing/sanitization/cleaners/joined.py
avwx/parsing/sanitization/cleaners/remove.py
avwx/parsing/sanitization/cleaners/replace.py
avwx/parsing/sanitization/cleaners/separated.py
avwx/parsing/sanitization/cleaners/temperature.py
avwx/parsing/sanitization/cleaners/visibility.py
avwx/parsing/sanitization/cleaners/wind.py
avwx/parsing/translate/__init__.py
avwx/parsing/translate/base.py
avwx/parsing/translate/metar.py
avwx/parsing/translate/remarks.py
avwx/parsing/translate/taf.py
avwx/service/__init__.py
avwx/service/base.py
avwx/service/bulk.py
avwx/service/files.py
avwx/service/scrape.py
avwx/static/__init__.py
avwx/static/airsigmet.py
avwx/static/core.py
avwx/static/gfs.py
avwx/static/glossary.py
avwx/static/metar.py
avwx/static/notam.py
avwx/static/taf.py
avwx/station/__init__.py
avwx/station/meta.py
avwx/station/search.py
avwx/station/station.py
avwx_engine-1.9.6.dist-info/METADATA
avwx_engine-1.9.6.dist-info/WHEEL
avwx_engine-1.9.6.dist-info/licenses/LICENSE
avwx_engine-1.9.6.dist-info/RECORD
