Metadata-Version: 2.4
Name: avwx-engine
Version: 1.9.6
Summary: Aviation weather report parsing library
Project-URL: Documentation, https://engine.avwx.rest
Project-URL: Homepage, https://engine.avwx.rest
Project-URL: Issues, https://github.com/avwx-rest/avwx-engine/issues
Project-URL: Source, https://github.com/avwx-rest/avwx-engine
Author-email: Michael duPont <michael@dupont.dev>
License-Expression: MIT
License-File: LICENSE
Keywords: aviation,metar,weather
Classifier: Development Status :: 5 - Production/Stable
Classifier: Intended Audience :: Developers
Classifier: License :: OSI Approved :: MIT License
Classifier: Operating System :: OS Independent
Classifier: Programming Language :: Python
Classifier: Programming Language :: Python :: 3
Classifier: Programming Language :: Python :: 3.10
Classifier: Programming Language :: Python :: 3.11
Classifier: Programming Language :: Python :: 3.12
Classifier: Programming Language :: Python :: 3.13
Classifier: Programming Language :: Python :: 3.14
Classifier: Topic :: Software Development :: Libraries :: Python Modules
Classifier: Typing :: Typed
Requires-Python: >=3.10
Requires-Dist: geopy>=2.4
Requires-Dist: httpx>=0.28
Requires-Dist: python-dateutil>=2.9
Requires-Dist: typing-extensions~=4.12; python_version < '3.11'
Requires-Dist: xmltodict>=0.13
Provides-Extra: all
Requires-Dist: numpy>=1.26; extra == 'all'
Requires-Dist: rapidfuzz>=3.6; extra == 'all'
Requires-Dist: scipy>=1.10; extra == 'all'
Requires-Dist: shapely>=2.0; extra == 'all'
Provides-Extra: fuzz
Requires-Dist: rapidfuzz>=3.6; extra == 'fuzz'
Provides-Extra: scipy
Requires-Dist: numpy>=1.26; extra == 'scipy'
Requires-Dist: scipy>=1.10; extra == 'scipy'
Provides-Extra: shape
Requires-Dist: shapely>=2.0; extra == 'shape'
